FetchRepo/RepoFetcher.py
FetchRepo/__init__.py
tests/RepoFetcherTester.py
tests/__init__.py
fetchrepo-2.1.2.dist-info/LICENSE
fetchrepo-2.1.2.dist-info/METADATA
fetchrepo-2.1.2.dist-info/WHEEL
fetchrepo-2.1.2.dist-info/top_level.txt
fetchrepo-2.1.2.dist-info/RECORD
