Metadata-Version: 2.1
Name: fetchrepo
Version: 2.1.2
Summary: Fetches and returns required content from github repository
Author: Al-Fareed
License-File: LICENSE
